tests/__init__.py
tests/test_embed_creator.py
tests/test_utils.py
whoisbuild/__init__.py
whoisbuild/embed_creator.py
whoisbuild/utils.py
whoisbuild-1.0.2.dist-info/LICENSE
whoisbuild-1.0.2.dist-info/METADATA
whoisbuild-1.0.2.dist-info/WHEEL
whoisbuild-1.0.2.dist-info/top_level.txt
whoisbuild-1.0.2.dist-info/RECORD
